dogma_data-0.2.19.dist-info/METADATA
dogma_data-0.2.19.dist-info/WHEEL
dogma_data-0.2.19.dist-info/entry_points.txt
dogma_data-0.2.19.dist-info/license_files/LICENSE
dogma_data/utils.py
dogma_data/__init__.py
dogma_data/dogma_rust.pyi
dogma_data/_hdf5_storage.py
dogma_data/_split.py
dogma_data/__main__.py
dogma_data/dogma_rust.cpython-312-x86_64-linux-gnu.so
dogma_data-0.2.19.dist-info/RECORD
