Metadata-Version: 2.3
Name: dogma-data
Version: 0.2.19
Requires-Dist: numpy
Requires-Dist: awkward
Requires-Dist: tqdm
Requires-Dist: numba ==0.60
Requires-Dist: blosc2
Requires-Dist: smart-open
Requires-Dist: click
License-File: LICENSE
Summary: Data processing for Dogma
Keywords: single-cell,RNA-seq,embedding,pytorch,uce
Author-email: Marcel Rød <roed@stanford.edu>
Requires-Python: >=3.10
Project-URL: Homepage, https://github.com/marcelroed/dogma-data
Project-URL: Repository, https://github.com/marcelroed/dogma-data.git
